ALU/alu.v
// Code your design here


module alu(
  input [3:0] A,
  input [3:0] B,
  input [2:0] CTRL,
  
  output reg [7:0] result,
  output reg Z,
  output reg C,
  output reg N,
  output reg E);
  
  reg [8:0] temp;
  
  always @(*) begin
    result=0;
    Z=0;
    C=0;
	N=0;
    E=0;
    
    case(CTRL)
      
      3'b000: begin
        temp=A+B;
        result=temp[7:0];
        C=temp[4];
      end
      
      3'b001: begin
        if(A>B)
          result=A-B;
        else begin
          N=1;
          result=B-A;
        end
      end
        
      3'b010: begin
        temp=A*B;
        result=temp[7:0];
        
      end
        
       3'b011: begin
         if(B==0) begin
           E=1;
           result=8'hff;
         end
         else begin
           result=A/B;
         end
       end
        
       3'b100: begin
         result=A&B;
        
       end
        
       3'b101: begin
         result=A|B;
       end
        
       3'b110: begin
         result=A^B;
       end
  
       3'b111: begin
         result=~A;
       end
    endcase
      
      if(result==0) begin
        Z=1;
      end
      
         
    end
  endmodule

ALU/alu_tb.v
`timescale 1ns/1ps

module alu_tb;

    reg  [3:0] A;
    reg  [3:0] B;
    reg  [2:0] CTRL;

    wire [7:0] result;
    wire Z;
    wire C;
    wire N;
    wire E;

    // Unit Under Test
    alu uut (
        .A(A),
        .B(B),
        .CTRL(CTRL),
        .result(result),
        .Z(Z),
        .C(C),
        .N(N),
        .E(E)
    );

    initial begin
      
        $dumpfile("dump.vcd");
        $dumpvars(0, alu_tb);

        $display("----------------------------------------------------");
        $display("CTRL\tA\tB\tRESULT\tZ\tC\tN\tE");
        $display("----------------------------------------------------");

        // Addition
        A = 4'd8;  B = 4'd7;  CTRL = 3'b000; #10;

        // Addition with carry
        A = 4'd15; B = 4'd15; CTRL = 3'b000; #10;

        // Subtraction (positive)
        A = 4'd10; B = 4'd4;  CTRL = 3'b001; #10;

        // Subtraction (negative flag)
        A = 4'd3;  B = 4'd7;  CTRL = 3'b001; #10;

        // Multiplication
        A = 4'd5;  B = 4'd3;  CTRL = 3'b010; #10;

        // Multiplication max case
        A = 4'd15; B = 4'd15; CTRL = 3'b010; #10;

        // Division
        A = 4'd8;  B = 4'd2;  CTRL = 3'b011; #10;

        // Divide by zero
        A = 4'd8;  B = 4'd0;  CTRL = 3'b011; #10;

        // AND
        A = 4'd12; B = 4'd10; CTRL = 3'b100; #10;

        // OR
        A = 4'd12; B = 4'd10; CTRL = 3'b101; #10;

        // XOR
        A = 4'd12; B = 4'd10; CTRL = 3'b110; #10;

        // NOT
        A = 4'd12; B = 4'd0;  CTRL = 3'b111; #10;

        $finish;

    end

    initial begin
        $monitor("%b\t%d\t%d\t%d\t%b\t%b\t%b\t%b",
                 CTRL, A, B, result, Z, C, N, E);
    end

endmodule

dump.vcd
$date
	Tue Jun 16 14:55:13 2026
$end
$version
	Icarus Verilog
$end
$timescale
	1ps
$end
$scope module alu_tb $end
$var wire 8 ! result [7:0] $end
$var wire 1 " Z $end
$var wire 1 # N $end
$var wire 1 $ E $end
$var wire 1 % C $end
$var reg 4 & A [3:0] $end
$var reg 4 ' B [3:0] $end
$var reg 3 ( CTRL [2:0] $end
$scope module uut $end
$var wire 4 ) A [3:0] $end
$var wire 4 * B [3:0] $end
$var wire 3 + CTRL [2:0] $end
$var reg 1 % C $end
$var reg 1 $ E $end
$var reg 1 # N $end
$var reg 1 " Z $end
$var reg 8 , result [7:0] $end
$var reg 9 - temp [8:0] $end
$upscope $end
$upscope $end
$enddefinitions $end
$comment Show the parameter values. $end
$dumpall
$end
#0
$dumpvars
b1111 -
b1111 ,
b0 +
b111 *
b1000 )
b0 (
b111 '
b1000 &
0%
0$
0#
0"
b1111 !
$end
#10000
1%
b11110 -
b11110 !
b11110 ,
b1111 '
b1111 *
b1111 &
b1111 )
#20000
0%
b110 !
b110 ,
b1 (
b1 +
b100 '
b100 *
b1010 &
b1010 )
#30000
1#
b100 !
b100 ,
b111 '
b111 *
b11 &
b11 )
#40000
b1111 -
0#
b1111 !
b1111 ,
b10 (
b10 +
b11 '
b11 *
b101 &
b101 )
#50000
b11100001 -
b11100001 !
b11100001 ,
b1111 '
b1111 *
b1111 &
b1111 )
#60000
b100 !
b100 ,
b11 (
b11 +
b10 '
b10 *
b1000 &
b1000 )
#70000
1$
b11111111 !
b11111111 ,
b0 '
b0 *
#80000
0$
b1000 !
b1000 ,
b100 (
b100 +
b1010 '
b1010 *
b1100 &
b1100 )
#90000
b1110 !
b1110 ,
b101 (
b101 +
#100000
b110 !
b110 ,
b110 (
b110 +
#110000
b11110011 !
b11110011 ,
b111 (
b111 +
b0 '
b0 *
